pytest_prometheus_pushgateway/__init__.py
pytest_prometheus_pushgateway/hooks.py
pytest_prometheus_pushgateway/plugin.py
pytest_prometheus_pushgateway/prometheus.py
pytest_prometheus_pushgateway/__pycache__/__init__.cpython-310-pytest-7.1.2.pyc
pytest_prometheus_pushgateway/__pycache__/__init__.cpython-310.pyc
pytest_prometheus_pushgateway/__pycache__/hooks.cpython-310-pytest-7.1.2.pyc
pytest_prometheus_pushgateway/__pycache__/plugin.cpython-310-pytest-7.1.2.pyc
pytest_prometheus_pushgateway/__pycache__/prometheus.cpython-310-pytest-7.1.2.pyc
pytest_prometheus_pushgateway-0.3.2.data/data/pytest_prometheus_pushgateway/__init__.cpython-310-pytest-7.1.2.pyc
pytest_prometheus_pushgateway-0.3.2.data/data/pytest_prometheus_pushgateway/__init__.cpython-310.pyc
pytest_prometheus_pushgateway-0.3.2.data/data/pytest_prometheus_pushgateway/hooks.cpython-310-pytest-7.1.2.pyc
pytest_prometheus_pushgateway-0.3.2.data/data/pytest_prometheus_pushgateway/plugin.cpython-310-pytest-7.1.2.pyc
pytest_prometheus_pushgateway-0.3.2.data/data/pytest_prometheus_pushgateway/prometheus.cpython-310-pytest-7.1.2.pyc
pytest_prometheus_pushgateway-0.3.2.dist-info/METADATA
pytest_prometheus_pushgateway-0.3.2.dist-info/WHEEL
pytest_prometheus_pushgateway-0.3.2.dist-info/entry_points.txt
pytest_prometheus_pushgateway-0.3.2.dist-info/top_level.txt
pytest_prometheus_pushgateway-0.3.2.dist-info/RECORD
